ldlite/__init__.py
ldlite/_camelcase.py
ldlite/_csv.py
ldlite/_jsonx.py
ldlite/_query.py
ldlite/_request.py
ldlite/_select.py
ldlite/_sqlx.py
ldlite/_xlsx.py
ldlite_rtr-0.1.1.dist-info/LICENSE
ldlite_rtr-0.1.1.dist-info/METADATA
ldlite_rtr-0.1.1.dist-info/WHEEL
ldlite_rtr-0.1.1.dist-info/RECORD
