Metadata-Version: 2.3
Name: ldlite-rtr
Version: 0.1.1
Summary: Lightweight analytics tool for Okapi-based services. Based on the original ldlite package from the Library Data Platform project: https://github.com/library-data-platform/ldlite
License: Apache-2.0
Keywords: okapi,folio,analytics,ldlite,reporting
Author: Nassib Nassar
Author-email: nassib@indexdata.com
Requires-Python: >=3.9,<4.0
Classifier: License :: OSI Approved :: Apache Software License
Classifier: Operating System :: OS Independent
Classifier: Programming Language :: Python :: 3
Classifier: Programming Language :: Python :: 3.9
Classifier: Programming Language :: Python :: 3.10
Classifier: Programming Language :: Python :: 3.11
Classifier: Programming Language :: Python :: 3.12
Classifier: Programming Language :: Python :: 3.13
Requires-Dist: duckdb (>=1.1.3,<2.0.0)
Requires-Dist: folioclient (>=0.61.3,<0.62.0)
Requires-Dist: psycopg2-binary (>=2.9.10,<3.0.0)
Requires-Dist: tqdm (>=4.67.1,<5.0.0)
Requires-Dist: xlsxwriter (>=3.2.0,<4.0.0)
Project-URL: Repository, https://github.com/bltravis/ldlite
